README.md
nufisdk/__init__.py
nufisdk/config.yaml
nufisdk/config_manager.py
nufisdk/main.py
nufisdk/model.py
nufisdk/sapeon_x330.py
nufisdk/stream_tester.py
nufisdk/utils.py
nufisdk/version.py
nufisdk-1.0.1.dist-info/METADATA
nufisdk-1.0.1.dist-info/WHEEL
nufisdk-1.0.1.dist-info/entry_points.txt
nufisdk-1.0.1.dist-info/RECORD
